velociraptor/__init__.py
velociraptor/__version__.py
velociraptor/exceptions.py
velociraptor/regex.py
velociraptor/units.py
velociraptor/velociraptor_compute_box_size_correction.py
velociraptor/velociraptor_plot.py
velociraptor/autoplotter/__init__.py
velociraptor/autoplotter/box_size_correction.py
velociraptor/autoplotter/compare.py
velociraptor/autoplotter/lines.py
velociraptor/autoplotter/metadata.py
velociraptor/autoplotter/objects.py
velociraptor/autoplotter/plot.py
velociraptor/catalogue/__init__.py
velociraptor/catalogue/catalogue.py
velociraptor/catalogue/derived.py
velociraptor/catalogue/registration.py
velociraptor/catalogue/soap_catalogue.py
velociraptor/catalogue/translator.py
velociraptor/catalogue/velociraptor_catalogue.py
velociraptor/fitting_formulae/__init__.py
velociraptor/fitting_formulae/smhmr.py
velociraptor/observations/__init__.py
velociraptor/observations/objects.py
velociraptor/particles/__init__.py
velociraptor/particles/particles.py
velociraptor/swift/__init__.py
velociraptor/swift/swift.py
velociraptor/tools/__init__.py
velociraptor/tools/adaptive.py
velociraptor/tools/histogram.py
velociraptor/tools/labels.py
velociraptor/tools/lines.py
velociraptor/tools/luminosity_functions.py
velociraptor/tools/mass_functions.py
velociraptor-0.20.0.dist-info/licenses/COPYING
velociraptor-0.20.0.dist-info/licenses/COPYING.LESSER
velociraptor-0.20.0.dist-info/METADATA
velociraptor-0.20.0.dist-info/WHEEL
velociraptor-0.20.0.dist-info/entry_points.txt
velociraptor-0.20.0.dist-info/top_level.txt
velociraptor-0.20.0.dist-info/RECORD
