Metadata-Version: 2.4
Name: velociraptor
Version: 0.20.0
Summary: Velociraptor catalogue reading routines.
Author-email: Josh Borrow <josh@joshborrow.com>, Kyle Oman <kyle.a.oman@durham.ac.uk>
Project-URL: Homepage, https://github.com/SWIFTSIM/velociraptor-python
Project-URL: Bug Tracker, https://github.com/SWIFTSIM/velociraptor-python/issues
Project-URL: Documentation, https://velociraptor-python.readthedocs.io/en/latest
Classifier: License :: OSI Approved :: GNU Lesser General Public License v3 or later (LGPLv3+)
Classifier: Operating System :: OS Independent
Requires-Python: >3.10.0
License-File: COPYING
License-File: COPYING.LESSER
Requires-Dist: numpy
Requires-Dist: h5py
Requires-Dist: unyt>=2.6.0
Requires-Dist: astropy
Dynamic: license-file
